mediainspect_rtsp/__init__.py
mediainspect_rtsp/config.py
mediainspect_rtsp/config_handler.py
mediainspect_rtsp/init.py
mediainspect_rtsp/main.py
mediainspect_rtsp/main_func.py
mediainspect_rtsp/network/__init__.py
mediainspect_rtsp/network/main.py
mediainspect_rtsp/network/models.py
mediainspect_rtsp/network/scanner.py
mediainspect_rtsp/network/scanner_worker.py
mediainspect_rtsp/network/utils.py
mediainspect_rtsp/network_scanner.py
mediainspect_rtsp/network_scanner_main.py
mediainspect_rtsp/network_service.py
mediainspect_rtsp/object_detector.py
mediainspect_rtsp/object_detector_class.py
mediainspect_rtsp/processing_stats.py
mediainspect_rtsp/rtsp.py
mediainspect_rtsp/rtsp_client.py
mediainspect_rtsp/rtsp_client_class.py
mediainspect_rtsp/simple_network_scanner.py
mediainspect_rtsp/test.py
mediainspect_rtsp/test_rtsp.py
mediainspect_rtsp/video_processor_cam.py
mediainspect_rtsp/video_processor_cam_class.py
mediainspect_rtsp/video_processor_rtsp.py
mediainspect_rtsp/video_processor_rtsp_class.py
mediainspect_rtsp/video_processor_rtsp_main.py
mediainspect_rtsp/web_rtsp_processor.py
mediainspect_rtsp/web_rtsp_processor_class.py
mediainspect_rtsp-0.1.4.dist-info/LICENSE
mediainspect_rtsp-0.1.4.dist-info/METADATA
mediainspect_rtsp-0.1.4.dist-info/WHEEL
mediainspect_rtsp-0.1.4.dist-info/RECORD
