Metadata-Version: 2.3
Name: mediainspect-rtsp
Version: 0.1.4
Summary: Real-time RTSP video stream processor with motion detection, object recognition, and analysis capabilities. Built with Python and OpenCV.
License: Apache-2.0
Keywords: rtsp,video,stream,opencv,object detection,motion detection,network,camera
Author: Tom Sapletta
Author-email: tom@mediainspect.com
Requires-Python: >=3.8,<4.0
Classifier: Intended Audience :: Developers
Classifier: Intended Audience :: End Users/Desktop
Classifier: License :: OSI Approved :: Apache Software License
Classifier: Operating System :: OS Independent
Classifier: Programming Language :: Python :: 3
Classifier: Programming Language :: Python :: 3.8
Classifier: Programming Language :: Python :: 3.9
Classifier: Programming Language :: Python :: 3.10
Classifier: Programming Language :: Python :: 3.11
Classifier: Programming Language :: Python :: 3.12
Classifier: Programming Language :: Python :: 3.13
Classifier: Topic :: Multimedia :: Video
Classifier: Topic :: Software Development :: Libraries :: Python Modules
Requires-Dist: dotenv
Requires-Dist: numpy
Requires-Dist: opencv-python
Requires-Dist: requests
Project-URL: Documentation, https://github.com/mediainspect/rtsp#readme
Project-URL: Homepage, https://pypi.org/project/mediainspect-rtsp/
Project-URL: Repository, https://github.com/mediainspect/rtsp
